reasoning_visualizer/__init__.py
reasoning_visualizer/app.py
reasoning_visualizer/frontend/build/asset-manifest.json
reasoning_visualizer/frontend/build/index.html
reasoning_visualizer/frontend/build/static/css/main.96fb6975.css
reasoning_visualizer/frontend/build/static/css/main.96fb6975.css.map
reasoning_visualizer/frontend/build/static/js/main.1644162f.js
reasoning_visualizer/frontend/build/static/js/main.1644162f.js.LICENSE.txt
reasoning_visualizer/frontend/build/static/js/main.1644162f.js.map
reasoning_visualizer/frontend/build/static/media/KaTeX_AMS-Regular.73ea273a72f4aca30ca5.woff2
reasoning_visualizer/frontend/build/static/media/KaTeX_AMS-Regular.853be92419a6c3766b9a.ttf
reasoning_visualizer/frontend/build/static/media/KaTeX_AMS-Regular.d562e886c52f12660a41.woff
reasoning_visualizer/frontend/build/static/media/KaTeX_Caligraphic-Bold.7489a2fbfb9bfe704420.ttf
reasoning_visualizer/frontend/build/static/media/KaTeX_Caligraphic-Bold.a1abf90dfd72792a577a.woff2
reasoning_visualizer/frontend/build/static/media/KaTeX_Caligraphic-Bold.d757c535a2e5902f1325.woff
reasoning_visualizer/frontend/build/static/media/KaTeX_Caligraphic-Regular.7e873d3833eb108a0758.ttf
reasoning_visualizer/frontend/build/static/media/KaTeX_Caligraphic-Regular.d6484fce1ef428d5bd94.woff2
reasoning_visualizer/frontend/build/static/media/KaTeX_Caligraphic-Regular.db074fa22cf224af93d7.woff
reasoning_visualizer/frontend/build/static/media/KaTeX_Fraktur-Bold.354501bac435c3264834.woff
reasoning_visualizer/frontend/build/static/media/KaTeX_Fraktur-Bold.4c761b3711973ab04edf.ttf
reasoning_visualizer/frontend/build/static/media/KaTeX_Fraktur-Bold.931d67ea207ab37ee693.woff2
reasoning_visualizer/frontend/build/static/media/KaTeX_Fraktur-Regular.172d3529b26f8cedef6b.woff2
reasoning_visualizer/frontend/build/static/media/KaTeX_Fraktur-Regular.6fdf0ac577be0ba82a4c.woff
reasoning_visualizer/frontend/build/static/media/KaTeX_Fraktur-Regular.ed305b5434865e06ffde.ttf
streamlit_reasoning_visualizer-0.1.0.dist-info/licenses/LICENSE
streamlit_reasoning_visualizer-0.1.0.dist-info/METADATA
streamlit_reasoning_visualizer-0.1.0.dist-info/WHEEL
streamlit_reasoning_visualizer-0.1.0.dist-info/top_level.txt
streamlit_reasoning_visualizer-0.1.0.dist-info/RECORD
