Metadata-Version: 2.4
Name: streamlit-reasoning-visualizer
Version: 0.1.0
Summary: A Streamlit component to visualize LLM reasoning processes with collapsible thought sections and rich markdown/LaTeX rendering
Home-page: https://github.com/ketanmahandule/streamlit-reasoning-visualizer
Author: Ketan Mahandule
License: Apache-2.0
Project-URL: Homepage, https://github.com/ketanmahandule/streamlit-reasoning-visualizer
Project-URL: Bug Tracker, https://github.com/ketanmahandule/streamlit-reasoning-visualizer/issues
Project-URL: Documentation, https://github.com/ketanmahandule/streamlit-reasoning-visualizer#readme
Project-URL: Source Code, https://github.com/ketanmahandule/streamlit-reasoning-visualizer
Keywords: streamlit,streamlit-component,reasoning,visualization,llm,chain-of-thought,ai,machine-learning
Classifier: Development Status :: 4 - Beta
Classifier: Environment :: Web Environment
Classifier: Intended Audience :: Developers
Classifier: Intended Audience :: Science/Research
Classifier: License :: OSI Approved :: Apache Software License
Classifier: Operating System :: OS Independent
Classifier: Programming Language :: Python :: 3
Classifier: Programming Language :: Python :: 3.8
Classifier: Programming Language :: Python :: 3.9
Classifier: Programming Language :: Python :: 3.10
Classifier: Programming Language :: Python :: 3.11
Classifier: Programming Language :: Python :: 3.12
Classifier: Topic :: Scientific/Engineering :: Artificial Intelligence
Classifier: Topic :: Software Development :: User Interfaces
Requires-Python: >=3.8
License-File: LICENSE
Requires-Dist: streamlit>=1.24.0
Provides-Extra: dev
Requires-Dist: pytest>=7.0.0; extra == "dev"
Requires-Dist: build>=1.0.0; extra == "dev"
Requires-Dist: twine>=4.0.0; extra == "dev"
Provides-Extra: example
Requires-Dist: ollama>=0.1.0; extra == "example"
Dynamic: home-page
Dynamic: license-file
Dynamic: requires-python
